ydata/sdk/VERSION
ydata/sdk/__init__.pyc
ydata/sdk/common/__init__.pyc
ydata/sdk/common/__init__.pyi
ydata/sdk/common/client/__init__.pyc
ydata/sdk/common/client/__init__.pyi
ydata/sdk/common/client/client.pyc
ydata/sdk/common/client/client.pyi
ydata/sdk/common/client/parser.pyc
ydata/sdk/common/client/parser.pyi
ydata/sdk/common/client/singleton.pyc
ydata/sdk/common/client/singleton.pyi
ydata/sdk/common/client/utils.pyc
ydata/sdk/common/client/utils.pyi
ydata/sdk/common/config.pyc
ydata/sdk/common/config.pyi
ydata/sdk/common/exceptions.pyc
ydata/sdk/common/exceptions.pyi
ydata/sdk/common/logger.pyc
ydata/sdk/common/logger.pyi
ydata/sdk/common/model.pyc
ydata/sdk/common/model.pyi
ydata/sdk/common/pydantic_utils.pyc
ydata/sdk/common/pydantic_utils.pyi
ydata/sdk/common/status.pyc
ydata/sdk/common/status.pyi
ydata/sdk/common/types.pyc
ydata/sdk/common/types.pyi
ydata/sdk/common/warnings.pyc
ydata/sdk/common/warnings.pyi
ydata/sdk/connectors/__init__.pyc
ydata/sdk/connectors/__init__.pyi
ydata/sdk/connectors/_models/__init__.pyc
ydata/sdk/connectors/_models/__init__.pyi
ydata/sdk/connectors/_models/connector.pyc
ydata/sdk/connectors/_models/connector.pyi
ydata/sdk/connectors/_models/connector_list.pyc
ydata/sdk/connectors/_models/connector_list.pyi
ydata/sdk/connectors/_models/connector_map.pyc
ydata/sdk/connectors/_models/connector_map.pyi
ydata/sdk/connectors/_models/connector_type.pyc
ydata/sdk/connectors/_models/connector_type.pyi
ydata/sdk/connectors/_models/credentials/__init__.pyc
ydata/sdk/connectors/_models/credentials/__init__.pyi
ydata/sdk/connectors/_models/credentials/awes3.pyc
ydata/sdk/connectors/_models/credentials/awes3.pyi
ydata/sdk/connectors/_models/credentials/azureblob.pyc
ydata/sdk/connectors/_models/credentials/azureblob.pyi
ydata/sdk/connectors/_models/credentials/azuresql.pyc
ydata/sdk/connectors/_models/credentials/azuresql.pyi
ydata/sdk/connectors/_models/credentials/bigquery.pyc
ydata/sdk/connectors/_models/credentials/bigquery.pyi
ydata_fabric_sdk-1.1.5.dist-info/LICENSE
ydata_fabric_sdk-1.1.5.dist-info/METADATA
ydata_fabric_sdk-1.1.5.dist-info/RECORD
ydata_fabric_sdk-1.1.5.dist-info/WHEEL
ydata_fabric_sdk-1.1.5.dist-info/top_level.txt
