Metadata-Version: 2.1
Name: ydata-fabric-sdk
Version: 1.1.5
Summary: YData SDK allows to use the *Data-Centric* tools from the YData ecosystem to accelerate AI development
Author-email: YData <opensource@ydata.ai>
License: MIT License
Project-URL: Home, https://github.com/ydataai/ydata-fabric-sdk
Classifier: License :: OSI Approved :: MIT License
Classifier: Development Status :: 5 - Production/Stable
Classifier: Intended Audience :: Developers
Classifier: Intended Audience :: Education
Classifier: Intended Audience :: End Users/Desktop
Classifier: Intended Audience :: Financial and Insurance Industry
Classifier: Intended Audience :: Healthcare Industry
Classifier: Intended Audience :: Science/Research
Classifier: Intended Audience :: Telecommunications Industry
Classifier: Operating System :: POSIX :: Linux
Classifier: Operating System :: MacOS
Classifier: Operating System :: Microsoft :: Windows
Classifier: Programming Language :: Python :: 3 :: Only
Classifier: Programming Language :: Python :: Implementation
Classifier: Topic :: Scientific/Engineering :: Artificial Intelligence
Classifier: Topic :: Software Development
Classifier: Topic :: Software Development :: Libraries :: Python Modules
Requires-Python: <3.13,>=3.10
License-File: LICENSE
Requires-Dist: httpx==0.28.*
Requires-Dist: ydata-core>=0.2.0
Requires-Dist: pandas>=1.5.0
Requires-Dist: prettytable==3.13.*
Requires-Dist: pydantic>=2.0.0
Requires-Dist: typeguard<2.14.0,>=2.13.3
Requires-Dist: ydata-datascience
Requires-Dist: requests==2.*
Provides-Extra: dev
Requires-Dist: twine; extra == "dev"
Requires-Dist: build; extra == "dev"
Requires-Dist: pylint==2.17.7; extra == "dev"
Requires-Dist: black==22.12.0; extra == "dev"
Requires-Dist: flake8==6.1.0; extra == "dev"
Requires-Dist: isort==5.12.0; extra == "dev"
Requires-Dist: pre-commit==2.21.0; extra == "dev"
Requires-Dist: pyc-wheel==1.2.7; extra == "dev"
Requires-Dist: mypy==1.14.1; extra == "dev"
Provides-Extra: doc
Requires-Dist: mkdocs<1.7.0,>=1.6.0; extra == "doc"
Requires-Dist: mkdocs-material<10.0.0,>=9.0.12; extra == "doc"
Requires-Dist: mkdocs-table-reader-plugin<=2.2.0; extra == "doc"
Requires-Dist: mike<2.2.0,>=2.1.1; extra == "doc"
Requires-Dist: mkdocstrings[python]<1.0.0,>=0.20.0; extra == "doc"
Requires-Dist: mkdocs-badges; extra == "doc"
Provides-Extra: test
Requires-Dist: pytest==6.2.5; extra == "test"
Requires-Dist: pytest-bdd==4.0.*; extra == "test"
Requires-Dist: pytest-cov==2.11.*; extra == "test"
Requires-Dist: pytest-xdist==2.2.*; extra == "test"
Requires-Dist: pytest-mccabe<3.0.0,>=2.0.0; extra == "test"
